{"items": [{"id": 1184702, "name": "Wikia Rokka no Yuusha", "hub": "Comics", "language": "es", "topic": "Anime", "domain": "es.rokka-no-yuusha.wikia.com", "wordmark": "https://vignette4.wikia.nocookie.net/rokka-no-yuusha/images/8/89/Wiki-wordmark.png/revision/latest?cb=20150810173930&path-prefix=es", "title": "Wikia Rokka no Yuusha", "url": "http://es.rokka-no-yuusha.wikia.com", "stats": {"edits": 684, "articles": 15, "pages": 301, "users": 18138977, "activeUsers": 0, "images": 45, "videos": 3, "admins": 1, "discussions": 1}, "topUsers": [1145657], "founding_user_id": "5905690", "creation_date": "2015-05-08 18:45:30", "headline": null, "lang": "es", "flags": [], "desc": "", "image": "", "wam_score": "2.2125"}, {"id": 1755437, "name": "Rokka no Yuusha \u0432\u0438\u043a\u0438", "hub": "Books", "language": "ru", "topic": "Anime", "domain": "ru.rokka-no-yuusha.wikia.com", "wordmark": "", "title": "Rokka no Yuusha \u0432\u0438\u043a\u0438", "url": "http://ru.rokka-no-yuusha.wikia.com", "stats": {"edits": 129, "articles": 5, "pages": 124, "users": 16638441, "activeUsers": 0, "images": 9, "videos": 0, "admins": 1, "discussions": 0}, "topUsers": [35916779, 1121346], "founding_user_id": "35916779", "creation_date": "2018-06-18 13:36:36", "headline": null, "lang": "ru", "flags": [], "desc": "", "image": "", "wam_score": 0}], "next": 0, "total": 2, "batches": 1, "currentBatch": 1}