{"items": [{"id": 512075, "name": "PewDiePie Wiki", "hub": "Games", "language": "en", "topic": "Gaming", "domain": "pewdiepie.wikia.com", "wordmark": "https://images.wikia.com/pewdiepie/images/8/89/Wiki-wordmark.png", "title": "PewDiePie Wiki", "url": "http://pewdiepie.wikia.com", "stats": {"edits": 48010, "articles": 867, "pages": 25951, "users": 18593470, "activeUsers": -1, "images": 1251, "videos": 560, "admins": 4}, "topUsers": [4513154, 35155246, 11546468, 35852041, 27661544, 34376308, 37584365, 33937723], "founding_user_id": "4573551", "creation_date": "2012-04-02 10:34:51", "headline": "Welcome to PerDiePie Wiki", "lang": "en", "flags": [], "desc": "Felix Arvid Ulf Kjellberg, also known as PewDiePie (pronounced pyoo-deh-pai), or PewDie and Pewds for short, is a 23 year-old Swedish video game commentator known for his videos on YouTube and appearances on numerous playthrough videos. PewDiePie is known for his Let's Plays on horror-themed video games, as well as playing many other types of games, including flash and indie games, and records his reactions through audio and webcam recording. PewDiePie's fanbase is known as the \"Bro Army\" which includes over 25,400,000 subscribers on YouTube.", "image": "https://images.wikia.nocookie.net/__cb20161102154725/pewdiepie/images/1/16/Wikia-Visualization-Main%2Cpewdiepie.png", "wam_score": "60.5464", "original_dimensions": {"width": 680, "height": 382}}, {"id": 584996, "name": "Pewdiepie Wiki", "hub": "TV", "language": "de", "topic": "Video Games", "domain": "de.pewdiepie.wikia.com", "wordmark": "https://vignette4.wikia.nocookie.net/pewdiepie/images/8/89/Wiki-wordmark.png/revision/latest?cb=20151221192550&path-prefix=de", "title": "Pewdiepie Wiki", "url": "http://de.pewdiepie.wikia.com", "stats": {"edits": 1350, "articles": 30, "pages": 781, "users": 16298674, "activeUsers": 0, "images": 65, "videos": 17, "admins": 2}, "topUsers": [], "founding_user_id": "3262285", "creation_date": "2012-08-12 17:26:05", "headline": "Willkommen zum PewDiePie Wikia", "lang": "de", "flags": [], "desc": "Erfahre im PewDiePie Wikia alles \u00fcber den Schreihals, der auf Youtube, als PewDiePie bekannt ist. Hier findest du alles zu seinen Let's Plays, zu seinen fiktiven Charakteren, Zu seinen Freunden und zu seiner Freundin Marzia, auch bekannt als CutiePieMarzia. Komm und helfe dem Wikia, in dem du bearbeitest / erstellst oder Bilder hinzuf\u00fcgst.", "image": "https://images.wikia.nocookie.net/__cb20161102160150/pewdiepie/de/images/0/02/Wikia-Visualization-Main%2Cdepewdiepie.png", "wam_score": "6.7067", "original_dimensions": {"width": 900, "height": 669}}, {"id": 705673, "name": "Ohgodnopewdiepie Wiki", "hub": "Lifestyle", "language": "en", "topic": "Video Games", "domain": "ohgodnopewdiepie.wikia.com", "wordmark": "", "title": "Ohgodnopewdiepie Wiki", "url": "http://ohgodnopewdiepie.wikia.com", "stats": {"edits": 372, "articles": 18, "pages": 287, "users": 15172166, "activeUsers": 0, "images": 23, "videos": 0, "admins": 1}, "topUsers": [], "founding_user_id": "7047155", "creation_date": "2013-03-09 14:43:14", "headline": null, "lang": "en", "flags": [], "desc": "", "image": "", "wam_score": 0}, {"id": 732942, "name": "PewDiePie Wiki", "hub": "TV", "language": "it", "topic": "Video Games", "domain": "it.pewdiepie.wikia.com", "wordmark": "", "title": "PewDiePie Wiki", "url": "http://it.pewdiepie.wikia.com", "stats": {"edits": 79, "articles": 2, "pages": 27, "users": 16324974, "activeUsers": 0, "images": 0, "videos": 0, "admins": 1, "discussions": 1}, "topUsers": [], "founding_user_id": "7763303", "creation_date": "2013-04-20 15:50:46", "headline": null, "lang": "it", "flags": [], "desc": "", "image": "", "wam_score": 0}, {"id": 1533369, "name": "Tuber Simulator Wiki", "hub": "Games", "language": "en", "topic": "Video Games", "domain": "tubersimulatorpewdiepie.wikia.com", "wordmark": "", "title": "Tuber Simulator Wiki", "url": "http://tubersimulatorpewdiepie.wikia.com", "stats": {"edits": 89, "articles": 6, "pages": 85, "users": 16531280, "activeUsers": 0, "images": 0, "videos": 0, "admins": 1, "discussions": 0}, "topUsers": [], "founding_user_id": "30602325", "creation_date": "2017-02-18 07:34:40", "headline": null, "lang": "en", "flags": [], "desc": "", "image": "", "wam_score": 0}], "next": 0, "total": 5, "batches": 1, "currentBatch": 1}