{"items": [{"id": 260417, "name": "Homeland TV Wiki", "hub": "TV", "language": "en", "topic": "Entertainment", "domain": "homeland.wikia.com", "wordmark": "https://images.wikia.com/homelandtv/images/8/89/Wiki-wordmark.png", "title": "Homeland TV Wiki", "url": "http://homeland.wikia.com", "stats": {"edits": 9253, "articles": 280, "pages": 2742, "users": 18518999, "activeUsers": -1, "images": 509, "videos": 63, "admins": 3, "discussions": 2}, "topUsers": [1264853, 34923596, 26635429, 32740624, 34872084, 34677666, 33284133, 29100309], "founding_user_id": "84037", "creation_date": "2011-05-02 02:25:33", "headline": "Welcome to the Homeland Wiki", "lang": "en", "flags": [], "desc": "Homeland is a psychological thriller television series which stars Damian Lewis as Gunnery Sergeant Nicholas Brody and Claire Danes as Carrie Mathison, a CIA operations officer who has come to believe that an American Marine, who was held captive by Al-Qaeda as a prisoner of war, was turned by the enemy and now poses a significant risk to national security.  Homeland Wiki is a collaborative encyclopedia for all aspects of this tv show which currently airs on the Showtime channel in the United States.", "image": "https://images.wikia.nocookie.net/__cb20161102152642/homelandtv/images/1/12/Wikia-Visualization-Main%2Chomelandtv.png", "wam_score": "38.3731", "original_dimensions": {"width": 536, "height": 358}}], "next": 0, "total": 1, "batches": 1, "currentBatch": 1}